README
setup.py
chouwa/__init__.py
chouwa/decorators.py
chouwa/defaultglobals.py
chouwa/environment.py
chouwa/loader.py
chouwa/shortcuts.py
chouwa/views.py
chouwa.egg-info/PKG-INFO
chouwa.egg-info/SOURCES.txt
chouwa.egg-info/dependency_links.txt
chouwa.egg-info/top_level.txt