Metadata-Version: 1.0
Name: chouwa
Version: 0.2.0
Summary: Django & Jinja2 integration
Home-page: http://bitbucket.org/trevor/chouwa
Author: Trevor Caira
Author-email: trevor@caira.com
License: UNKNOWN
Platform: UNKNOWN
Classifier: Development Status :: 3 - Alpha
Classifier: Environment :: Web Environment
Classifier: Framework :: Django
Classifier: Intended Audience :: Developers
Classifier: License :: OSI Approved :: MIT License
Classifier: Operating System :: OS Independent
Classifier: Programming Language :: Python
Classifier: Topic :: Internet :: WWW/HTTP :: Dynamic Content
Classifier: Topic :: Software Development :: Libraries :: Python Modules
